defer/__init__.py
defer/_defer.py
defer/defer.py
defer/errors.py
defer/sugar/__init__.py
defer/sugar/_parse.py
defer/sugar/transformer.py
defer/sugarfree/__init__.py
python_defer-0.2.1.dist-info/METADATA
python_defer-0.2.1.dist-info/WHEEL
python_defer-0.2.1.dist-info/RECORD
